Workbook
Name \a: #N/A
Name \c: #N/A
Name \f: #N/A
Name \i: #REF!
Name \l: #REF!
Name __G1002686: '[1]Anexo I (2)'!#REF!
Name _G1002686: '[1]Anexo I (2)'!#REF!
Name a: #REF!
Name aa: '[1]Anexo I (2)'!#REF!
Name Abcd: [2]AUTORES!#REF!
Name Agências_Setores: #REF!
Name agexcel: #REF!
Name aloca: #REF!
Name ANEXO: #REF!
Name ANEXOB: '[1]Anexo I (2)'!#REF!
Name APAGA: #N/A
Name AREA: [2]AUTORES!#REF!
Name area2: [2]AUTORES!#REF!
Name area3: [3]AUTORES!#REF!
Name banco: #REF!
Name compensacao: [2]AUTORES!#REF!
Name compensacao1: '[1]Anexo I (2)'!#REF!
Name CONTADOR: #N/A
Name D: #REF!
Name Dados: #REF!
Name data: #REF!
Name DATA_ATUAL: #REF!
Name Débitos: #REF!
Name descrição: '[4]Anexo A'!#REF!
Name DIARIO1B: #REF!
Name DIARIO1E: #REF!
Name DIARIO2A: #REF!
Name DIARIO2B: #REF!
Name DIARIO2E: #REF!
Name DT_ATUAL: #REF!
Name Erro: #REF!
Name Erro2: #REF!
Name Erro3: #REF!
Name f: #REF!
Name g: #REF!
Name G_ÿ_P_: #REF!
Name guilherme: '[5]Anexo B'!#REF!
Name INFLAÇÃO: #REF!
Name ing: #REF!
Name inpc: #REF!
Name J276J276: #REF!
Name LIBOR: #REF!
Name MENSAL2: #REF!
Name MENSAL4: #REF!
Name MESTRE2: [6]BTNF_TRD!#REF!
Name NOVO: [6]BTNF_TRD!#REF!
Name NUCLEO: #N/A
Name Per: #REF!
Name Período: #REF!
Name plan: [2]AUTORES!#REF!
Name PMi: '[7]Relat Inf 0009 - graf'!$H$4:$L$16
Name PMp: '[7]Relat Inf 0009 - graf'!$B$4:$F$16
Name port: #REF!
Name Print_Area_MI: '[8]Quadro 1'!#REF!
Name Quadro_II___Base_monetária_e_componentes: #REF!

Sheet DADOS
A1: Campo | B1: Valor
A2: Título da operação
A3: Data de emissão
A4: 1º vencimento
A5: Último vencimento
A6: Valor principal
A7: TAC / tarifas
A8: IOF
A9: Quantidade de parcelas
A10: Valor da prestação
A11: Taxa pactuada (mensal)
A12: Taxa BACEN (mensal)
A13: Parcelas pagas
A14: Data do cálculo

Sheet PRICE 24X
C1: =DADOS!$B$2
C3: Data da pactuação: | D3: =DADOS!$B$3
C4: Data do cálculo: | D4: =TODAY()
C5: Data do 1º vencimento: | D5: =DADOS!$B$4
C6: DADOS DO CONTRATO | AD6: VALORES RECALCULADOS | BE6: SALDO RECALCULADO DESCONTANDO AS PARCELAS PAGAS
C7: Valor principal financiado = | I7: =DADOS!$B$6 | AD7: Valor principal financiado = | AP7: =I7 | BE7: Saldo devedor total do contrato = | BL7: =AP17
C8: Seguros = | I8: 0 | AD8: Seguros = | AP8: 0 | BE8: Quantidade de parcelas pagas= | BL8: =DADOS!$B$13
C9: TAC = | I9: =DADOS!$B$7 | AD9: TAC = | AP9: 0 | BE9: Valor da parcela paga = | BL9: =I16
C10: Registro = | I10: 0 | AD10: Registro = | AP10: 0 | BE10: Valor total pago pelo cliente = | BL10: =BL8*BL9
C11: Avaliação = | I11: 0 | AD11: Avaliação = | AP11: 0 | BE11: Saldo devedor atualizado = | BL11: =BL7-BL10
C12: Outros = | I12: 0 | AD12: Outros = | AP12: 0 | BE12: Quantidade de parcelas a vencer = | BL12: =I15-BL8
C13: IOF = | I13: =DADOS!$B$8 | AD13: IOF = | AP13: =I13 | BE13: Valor da parcela atual = | BL13: =BL11/BL12
C14: Valor financiado total no contrato = | I14: =SUM(I7:Y13) | AD14: Valor financiado total no contrato = | AP14: =SUM(AP7:AZ13)
C15: Quantidade de parcelas = | I15: =DADOS!$B$9 | AD15: Taxa média = | AP15: =DADOS!$B$12
C16: Valor da parcela cobrada = | I16: =DADOS!$B$10 | AD16: Valor da parcela recalculada = | AP16: =AH121 | BE16: Saldo do contrato = | BL16: =BL12*I16
C17: Taxa pactuada = | I17: =DADOS!$B$11 | AD17: Valor final recalculado do contrato = | AP17: =I15*AP16 | BE17: (-) Saldo incontroverso = | BL17: =BL12*BL13
C18: Valor final do contrato = | I18: =I15*I16 | AD18: Diferença cobrada a mais por parcela = | AP18: =I16-AP16 | BE18: Saldo controvertido total = | BL18: =BL16-BL17
AD19: Montante cobrado a mais pelo banco = | AP19: =I18-AP17 | BE19: Saldo controvertido por parcela = | BL19: =BL18/BL12
BE23: Saldo controvertido por parcela
C25: CONFORME PACTUADO | AD25: PARCELA COM TAXA MÉDIA E EXPURGO DE ABUSIVIDADES
C29: Valor financiado total = | H29: =I14 | AD29: Valor financiado ajustado = (com expurgo de tarifas e/ou seguros) | AI29: =AP14 | BE29: PERCENTUAL DA TAXA COBRADADA SUPERIOR A MÉDIA | BK29: TOTAL NOMINAL DE COBRANÇAS INDEVIDAS
C30: Taxa de juros ao mês = | H30: =I17 | AD30: Taxa média de juros ao mês = | AI30: =AP15 | BE30: =H30/AI30-100% | BK30: =SUM(I8:Y12)
C31: Quantidade de parcelas = | I31: =I15 | AD31: Quantidade de parcelas = | AJ31: =I15
C33: Valor da parcela | E33: = | G33: PV | I33: x | O33: 1 | Q33: + | S33: i | U33: n | W33: x | Y33: i | AD33: Valor da parcela | AF33: = | AH33: PV | AJ33: x | AP33: 1 | AR33: + | AT33: i | AV33: n | AX33: x | AZ33: i
BE38: TAXA EFETIVAMENTE COBRADA
O41: 1 | Q41: + | S41: i | U41: n | W41: - | Y41: 1 | AP41: 1 | AR41: + | AT41: i | AV41: n | AX41: - | AZ41: 1
BE45: =RATE(I15,I16,-I14)
C49: Valor da parcela | E49: = | G49: =H29 | I49: x | O49: 1 | Q49: + | S49: =H30 | U49: =I31 | W49: x | Y49: =S49 | AD49: Valor da parcela | AF49: = | AH49: =AI29 | AJ49: x | AP49: 1 | AR49: + | AT49: =AI30 | AV49: =AJ31 | AX49: x | AZ49: =AT49
O57: 1 | Q57: + | S57: =S49 | U57: =U49 | W57: - | Y57: 1 | AP57: 1 | AR57: + | AT57: =AT49 | AV57: =AV49 | AX57: - | AZ57: 1
C65: PMT | E65: = | G65: =G49 | I65: x | O65: =O49+S49 | U65: =U49 | W65: x | Y65: =Y49 | AD65: PMT | AF65: = | AH65: =AH49 | AJ65: x | AP65: =AP49+AT49 | AV65: =AV49 | AX65: x | AZ65: =AZ49
O73: =O65 | U73: =U49 | W73: - | Y73: 1 | AP73: =AP65 | AV73: =AV49 | AX73: - | AZ73: 1
C81: PMT | E81: = | G81: =G65 | I81: x | O81: =POWER(O65,U65) | W81: x | Y81: =Y65 | AD81: PMT | AF81: = | AH81: =AH65 | AJ81: x | AP81: =POWER(AP65,AV65) | AX81: x | AZ81: =AZ65
O89: =O81 | W89: - | Y89: 1 | AP89: =AP81 | AX89: - | AZ89: 1
C97: PMT | E97: = | G97: =G81 | I97: x | O97: =O81*Y81 | AD97: PMT | AF97: = | AH97: =AH81 | AJ97: x | AP97: =AP81*AZ81
O105: =O89-Y89 | AP105: =AP89-AZ89
C113: PMT | E113: = | G113: =G97 | I113: x | K113: =O97/O105 | AD113: PMT | AF113: = | AH113: =AH97 | AJ113: x | AL113: =AP97/AP105
C121: Valor da parcela | E121: = | G121: =(G113*K113) | AD121: Valor da parcela | AF121: = | AH121: =(AH113*AL113)
C130: PARCELAS CONFORME O CONTRATO | AD130: PARCELAS RECALCULADAS | BE130: VALORES PAGOS PELO CLIENTE
C131: Parcela | D131: Vencimento | N131: Parcela cobrada | AD131: Parcela | AE131: Vencimento | AO131: Parcela recalculada | BE131: Parcela | BF131: Vencimento | BP131: Valor pago
C132: 1 | D132: =IF(C132<=$I$15, $D$5, "") | N132: =IF(C132<=$I$15, $I$16, "") | AD132: 1 | AE132: =D132 | AO132: =AH121 | BE132: 1 | BF132: =AE132 | BP132: =N132
C133: 2 | D133: =IF(C133<=$I$15, EDATE($D$5, C133-1), "") | N133: =IF(C133<=$I$15, $I$16, "") | AD133: 2 | AE133: =D133 | AO133: =AO132 | BE133: 2 | BF133: =AE133 | BP133: =BP132
C134: 3 | D134: =IF(C134<=$I$15, EDATE($D$5, C134-1), "") | N134: =IF(C134<=$I$15, $I$16, "") | AD134: 3 | AE134: =D134 | AO134: =AO133 | BE134: 3 | BF134: =AE134 | BP134: =BP133
C135: 4 | D135: =IF(C135<=$I$15, EDATE($D$5, C135-1), "") | N135: =IF(C135<=$I$15, $I$16, "") | AD135: 4 | AE135: =D135 | AO135: =AO134 | BE135: 4 | BF135: =AE135 | BP135: 0
C136: 5 | D136: =IF(C136<=$I$15, EDATE($D$5, C136-1), "") | N136: =IF(C136<=$I$15, $I$16, "") | AD136: 5 | AE136: =D136 | AO136: =AO135 | BE136: 5 | BF136: =AE136 | BP136: =BP135
C137: 6 | D137: =IF(C137<=$I$15, EDATE($D$5, C137-1), "") | N137: =IF(C137<=$I$15, $I$16, "") | AD137: 6 | AE137: =D137 | AO137: =AO136 | BE137: 6 | BF137: =AE137 | BP137: =BP136
C138: 7 | D138: =IF(C138<=$I$15, EDATE($D$5, C138-1), "") | N138: =IF(C138<=$I$15, $I$16, "") | AD138: 7 | AE138: =D138 | AO138: =AO137 | BE138: 7 | BF138: =AE138 | BP138: =BP137
C139: 8 | D139: =IF(C139<=$I$15, EDATE($D$5, C139-1), "") | N139: =IF(C139<=$I$15, $I$16, "") | AD139: 8 | AE139: =D139 | AO139: =AO138 | BE139: 8 | BF139: =AE139 | BP139: =BP138
C140: 9 | D140: =IF(C140<=$I$15, EDATE($D$5, C140-1), "") | N140: =IF(C140<=$I$15, $I$16, "") | AD140: 9 | AE140: =D140 | AO140: =AO139 | BE140: 9 | BF140: =AE140 | BP140: =BP139
C141: 10 | D141: =IF(C141<=$I$15, EDATE($D$5, C141-1), "") | N141: =IF(C141<=$I$15, $I$16, "") | AD141: 10 | AE141: =D141 | AO141: =AO140 | BE141: 10 | BF141: =AE141 | BP141: =BP140
C142: 11 | D142: =IF(C142<=$I$15, EDATE($D$5, C142-1), "") | N142: =IF(C142<=$I$15, $I$16, "") | AD142: 11 | AE142: =D142 | AO142: =AO141 | BE142: 11 | BF142: =AE142 | BP142: 0
C143: 12 | D143: =IF(C143<=$I$15, EDATE($D$5, C143-1), "") | N143: =IF(C143<=$I$15, $I$16, "") | AD143: 12 | AE143: =D143 | AO143: =AO142 | BE143: 12 | BF143: =AE143 | BP143: 0
C144: 13 | D144: =IF(C144<=$I$15, EDATE($D$5, C144-1), "") | N144: =IF(C144<=$I$15, $I$16, "") | AD144: 13 | AE144: =D144 | AO144: =AO143 | BE144: 13 | BF144: =AE144 | BP144: 0
C145: 14 | D145: =IF(C145<=$I$15, EDATE($D$5, C145-1), "") | N145: =IF(C145<=$I$15, $I$16, "") | AD145: 14 | AE145: =D145 | AO145: =AO144 | BE145: 14 | BF145: =AE145 | BP145: =BP144
C146: 15 | D146: =IF(C146<=$I$15, EDATE($D$5, C146-1), "") | N146: =IF(C146<=$I$15, $I$16, "") | AD146: 15 | AE146: =D146 | AO146: =AO145 | BE146: 15 | BF146: =AE146 | BP146: =BP145
C147: 16 | D147: =IF(C147<=$I$15, EDATE($D$5, C147-1), "") | N147: =IF(C147<=$I$15, $I$16, "") | AE147: =D147 | BF147: =AE147
C148: 17 | D148: =IF(C148<=$I$15, EDATE($D$5, C148-1), "") | N148: =IF(C148<=$I$15, $I$16, "") | AE148: =D148 | BF148: =AE148
C149: 18 | D149: =IF(C149<=$I$15, EDATE($D$5, C149-1), "") | N149: =IF(C149<=$I$15, $I$16, "") | AE149: =D149 | BF149: =AE149
C150: 19 | D150: =IF(C150<=$I$15, EDATE($D$5, C150-1), "") | N150: =IF(C150<=$I$15, $I$16, "") | AE150: =D150 | BF150: =AE150
C151: 20 | D151: =IF(C151<=$I$15, EDATE($D$5, C151-1), "") | N151: =IF(C151<=$I$15, $I$16, "") | AE151: =D151 | BF151: =AE151
C152: 21 | D152: =IF(C152<=$I$15, EDATE($D$5, C152-1), "") | N152: =IF(C152<=$I$15, $I$16, "") | AE152: =D152 | BF152: =AE152
C153: 22 | D153: =IF(C153<=$I$15, EDATE($D$5, C153-1), "") | N153: =IF(C153<=$I$15, $I$16, "") | AE153: =D153 | BF153: =AE153
C154: 23 | D154: =IF(C154<=$I$15, EDATE($D$5, C154-1), "") | N154: =IF(C154<=$I$15, $I$16, "") | AE154: =D154 | BF154: =AE154
C155: 24 | D155: =IF(C155<=$I$15, EDATE($D$5, C155-1), "") | N155: =IF(C155<=$I$15, $I$16, "") | AE155: =D155 | BF155: =AE155

Sheet PRICE 36x
C2: =DADOS!$B$2
C4: Data da pactuação: | D4: =DADOS!$B$3
C5: Data do cálculo: | D5: =TODAY()
C6: Data do 1º vencimento: | D6: =DADOS!$B$4
C7: DADOS DO CONTRATO | AD7: VALORES RECALCULADOS | BE7: SALDO RECALCULADO DESCONTANDO AS PARCELAS PAGAS
C8: Valor principal financiado = | I8: =DADOS!$B$6 | AD8: Valor principal financiado = | AP8: =I8 | BE8: Saldo devedor total do contrato = | BL8: =AP18
C9: Seguros = | AD9: Seguros = | AP9: 0 | BE9: Quantidade de parcelas pagas= | BL9: =DADOS!$B$13
C10: TAC = | I10: =DADOS!$B$7 | AD10: TAC = | AP10: 0 | BE10: Valor da parcela paga = | BL10: =I17
C11: Registro = | AD11: Registro = | AP11: 0 | BE11: Valor total pago pelo cliente = | BL11: =BL9*BL10
C12: Avaliação = | AD12: Avaliação = | AP12: 0 | BE12: Saldo devedor atualizado = | BL12: =BL8-BL11
C13: Outros = | AD13: Outros = | AP13: 0 | BE13: Quantidade de parcelas a vencer = | BL13: =I16-BL9
C14: IOF = | I14: =DADOS!$B$8 | AD14: IOF = | AP14: =I14 | BE14: Valor da parcela atual = | BL14: =BL12/BL13
C15: Valor financiado total no contrato = | I15: =SUM(I8:Y14) | AD15: Valor financiado total no contrato = | AP15: =SUM(AP8:AZ14)
C16: Quantidade de parcelas = | I16: =DADOS!$B$9 | AD16: Taxa média = | AP16: =DADOS!$B$12
C17: Valor da parcela cobrada = | I17: =DADOS!$B$10 | AD17: Valor da parcela recalculada = | AP17: =AH122 | BE17: Saldo do contrato = | BL17: =BL13*I17
C18: Taxa pactuada = | I18: =DADOS!$B$11 | AD18: Valor final recalculado do contrato = | AP18: =I16*AP17 | BE18: (-) Saldo incontroverso = | BL18: =BL13*BL14
C19: Valor final do contrato = | I19: =I16*I17 | AD19: Diferença cobrada a mais por parcela = | AP19: =I17-AP17 | BE19: Saldo controvertido total = | BL19: =BL17-BL18
AD20: Montante cobrado a mais pelo banco = | AP20: =I19-AP18 | BE20: Saldo controvertido por parcela = | BL20: =BL19/BL13
BE24: Saldo controvertido por parcela
C26: CONFORME PACTUADO | AD26: PARCELA COM TAXA MÉDIA E EXPURGO DE ABUSIVIDADES
C30: Valor financiado total = | H30: =I15 | AD30: Valor financiado ajustado = (com expurgo de tarifas e/ou seguros) | AI30: =AP15 | BE30: PERCENTUAL DA TAXA COBRADADA SUPERIOR A MÉDIA | BK30: TOTAL NOMINAL DE COBRANÇAS INDEVIDAS
C31: Taxa de juros ao mês = | H31: =I18 | AD31: Taxa média de juros ao mês = | AI31: =AP16 | BE31: =H31/AI31-100% | BK31: =SUM(I9:Y13)
C32: Quantidade de parcelas = | I32: =I16 | AD32: Quantidade de parcelas = | AJ32: =I16
C34: Valor da parcela | E34: = | G34: PV | I34: x | O34: 1 | Q34: + | S34: i | U34: n | W34: x | Y34: i | AD34: Valor da parcela | AF34: = | AH34: PV | AJ34: x | AP34: 1 | AR34: + | AT34: i | AV34: n | AX34: x | AZ34: i
BE39: TAXA EFETIVAMENTE COBRADA
O42: 1 | Q42: + | S42: i | U42: n | W42: - | Y42: 1 | AP42: 1 | AR42: + | AT42: i | AV42: n | AX42: - | AZ42: 1
BE46: =RATE(I16,I17,-I15)
C50: Valor da parcela | E50: = | G50: =H30 | I50: x | O50: 1 | Q50: + | S50: =H31 | U50: =I32 | W50: x | Y50: =S50 | AD50: Valor da parcela | AF50: = | AH50: =AI30 | AJ50: x | AP50: 1 | AR50: + | AT50: =AI31 | AV50: =AJ32 | AX50: x | AZ50: =AT50
O58: 1 | Q58: + | S58: =S50 | U58: =U50 | W58: - | Y58: 1 | AP58: 1 | AR58: + | AT58: =AT50 | AV58: =AV50 | AX58: - | AZ58: 1
C66: PMT | E66: = | G66: =G50 | I66: x | O66: =O50+S50 | U66: =U50 | W66: x | Y66: =Y50 | AD66: PMT | AF66: = | AH66: =AH50 | AJ66: x | AP66: =AP50+AT50 | AV66: =AV50 | AX66: x | AZ66: =AZ50
O74: =O66 | U74: =U50 | W74: - | Y74: 1 | AP74: =AP66 | AV74: =AV50 | AX74: - | AZ74: 1
C82: PMT | E82: = | G82: =G66 | I82: x | O82: =POWER(O66,U66) | W82: x | Y82: =Y66 | AD82: PMT | AF82: = | AH82: =AH66 | AJ82: x | AP82: =POWER(AP66,AV66) | AX82: x | AZ82: =AZ66
O90: =O82 | W90: - | Y90: 1 | AP90: =AP82 | AX90: - | AZ90: 1
C98: PMT | E98: = | G98: =G82 | I98: x | O98: =O82*Y82 | AD98: PMT | AF98: = | AH98: =AH82 | AJ98: x | AP98: =AP82*AZ82
O106: =O90-Y90 | AP106: =AP90-AZ90
C114: PMT | E114: = | G114: =G98 | I114: x | K114: =O98/O106 | AD114: PMT | AF114: = | AH114: =AH98 | AJ114: x | AL114: =AP98/AP106
C122: Valor da parcela | E122: = | G122: =(G114*K114) | AD122: Valor da parcela | AF122: = | AH122: =(AH114*AL114)
C131: PARCELAS CONFORME O CONTRATO | AD131: PARCELAS RECALCULADAS | BE131: VALORES PAGOS PELO CLIENTE
C132: Parcela | D132: Vencimento | N132: Parcela cobrada | AD132: Parcela | AE132: Vencimento | AO132: Parcela recalculada | BE132: Parcela | BF132: Vencimento | BP132: Valor pago
C133: 1 | D133: =IF(C133<=$I$16, $D$6, "") | N133: =IF(C133<=$I$16, $I$17, "") | AD133: 1 | AE133: =D133 | AO133: =AH122 | BE133: 1 | BF133: =AE133 | BP133: =N133
C134: 2 | D134: =IF(C134<=$I$16, EDATE($D$6, C134-1), "") | N134: =IF(C134<=$I$16, $I$17, "") | AD134: 2 | AE134: =D134 | AO134: =AO133 | BE134: 2 | BF134: =AE134 | BP134: =BP133
C135: 3 | D135: =IF(C135<=$I$16, EDATE($D$6, C135-1), "") | N135: =IF(C135<=$I$16, $I$17, "") | AD135: 3 | AE135: =D135 | AO135: =AO134 | BE135: 3 | BF135: =AE135
C136: 4 | D136: =IF(C136<=$I$16, EDATE($D$6, C136-1), "") | N136: =IF(C136<=$I$16, $I$17, "") | AD136: 4 | AE136: =D136 | AO136: =AO135 | BE136: 4 | BF136: =AE136
C137: 5 | D137: =IF(C137<=$I$16, EDATE($D$6, C137-1), "") | N137: =IF(C137<=$I$16, $I$17, "") | AD137: 5 | AE137: =D137 | AO137: =AO136 | BE137: 5 | BF137: =AE137
C138: 6 | D138: =IF(C138<=$I$16, EDATE($D$6, C138-1), "") | N138: =IF(C138<=$I$16, $I$17, "") | AD138: 6 | AE138: =D138 | AO138: =AO137 | BE138: 6 | BF138: =AE138
C139: 7 | D139: =IF(C139<=$I$16, EDATE($D$6, C139-1), "") | N139: =IF(C139<=$I$16, $I$17, "") | AD139: 7 | AE139: =D139 | AO139: =AO138 | BE139: 7 | BF139: =AE139
C140: 8 | D140: =IF(C140<=$I$16, EDATE($D$6, C140-1), "") | N140: =IF(C140<=$I$16, $I$17, "") | AD140: 8 | AE140: =D140 | AO140: =AO139 | BE140: 8 | BF140: =AE140
C141: 9 | D141: =IF(C141<=$I$16, EDATE($D$6, C141-1), "") | N141: =IF(C141<=$I$16, $I$17, "") | AD141: 9 | AE141: =D141 | AO141: =AO140 | BE141: 9 | BF141: =AE141
C142: 10 | D142: =IF(C142<=$I$16, EDATE($D$6, C142-1), "") | N142: =IF(C142<=$I$16, $I$17, "") | AD142: 10 | AE142: =D142 | AO142: =AO141 | BE142: 10 | BF142: =AE142
C143: 11 | D143: =IF(C143<=$I$16, EDATE($D$6, C143-1), "") | N143: =IF(C143<=$I$16, $I$17, "") | AD143: 11 | AE143: =D143 | AO143: =AO142 | BE143: 11 | BF143: =AE143
C144: 12 | D144: =IF(C144<=$I$16, EDATE($D$6, C144-1), "") | N144: =IF(C144<=$I$16, $I$17, "") | AD144: 12 | AE144: =D144 | AO144: =AO143 | BE144: 12 | BF144: =AE144
C145: 13 | D145: =IF(C145<=$I$16, EDATE($D$6, C145-1), "") | N145: =IF(C145<=$I$16, $I$17, "") | AD145: 13 | AE145: =D145 | AO145: =AO144 | BE145: 13 | BF145: =AE145
C146: 14 | D146: =IF(C146<=$I$16, EDATE($D$6, C146-1), "") | N146: =IF(C146<=$I$16, $I$17, "") | AD146: 14 | AE146: =D146 | AO146: =AO145 | BE146: 14 | BF146: =AE146
... C168: 36 | D168: =IF(C168<=$I$16, EDATE($D$6, C168-1), "") | N168: =IF(C168<=$I$16, $I$17, "") | AD168: 36 | AE168: =D168 | AO168: =AO167 | BE168: 36 | BF168: =AE168

Sheet PRICE 48x
C2: =DADOS!$B$2
C4: Data da pactuação: | D4: =DADOS!$B$3
C5: Data do cálculo: | D5: =TODAY()
C6: Data do 1º vencimento: | D6: =DADOS!$B$4
C7: DADOS DO CONTRATO | AD7: VALORES RECALCULADOS | BE7: SALDO RECALCULADO DESCONTANDO AS PARCELAS PAGAS
C8: Valor principal financiado = | I8: =DADOS!$B$6 | AD8: Valor principal financiado = | BE8: Saldo devedor total do contrato = | BL8: =AP18
C9: Seguros = | AD9: Seguros = | AP9: 0 | BE9: Quantidade de parcelas pagas= | BL9: =DADOS!$B$13
C10: TAC = | I10: =DADOS!$B$7 | AD10: TAC = | AP10: 0 | BE10: Valor da parcela paga = | BL10: =I17
C11: Registro = | AD11: Registro = | BE11: Valor total pago pelo cliente = | BL11: =BL9*BL10
C12: Avaliação = | AD12: Avaliação = | AP12: 0 | BE12: Saldo devedor atualizado = | BL12: =BL8-BL11
C13: Outros = | AD13: Outros = | AP13: 0 | BE13: Quantidade de parcelas a vencer = | BL13: =I16-BL9
C14: IOF = | I14: =DADOS!$B$8 | AD14: IOF = | AP14: =I14 | BE14: Valor da parcela atual = | BL14: =BL12/BL13
C15: Valor financiado total no contrato = | AD15: Valor financiado total no contrato = | AP15: =SUM(AP8:AZ14)
C16: Quantidade de parcelas = | I16: =DADOS!$B$9 | AD16: Taxa média = | AP16: =DADOS!$B$12
C17: Valor da parcela cobrada = | I17: =DADOS!$B$10 | AD17: Valor da parcela recalculada = | AP17: =AH122 | BE17: Saldo do contrato = | BL17: =BL13*I17
C18: Taxa pactuada = | I18: =DADOS!$B$11 | AD18: Valor final recalculado do contrato = | AP18: =I16*AP17 | BE18: (-) Saldo incontroverso = | BL18: =BL13*BL14
C19: Valor final do contrato = | I19: =I16*I17 | AD19: Diferença cobrada a mais por parcela = | AP19: =I17-AP17 | BE19: Saldo controvertido total = | BL19: =BL17-BL18
AD20: Montante cobrado a mais pelo banco = | AP20: =I19-AP18 | BE20: Saldo controvertido por parcela = | BL20: =BL19/BL13
BE24: Saldo controvertido por parcela
C26: CONFORME PACTUADO | AD26: PARCELA COM TAXA MÉDIA E EXPURGO DE ABUSIVIDADES
C30: Valor financiado total = | H30: =I15 | AD30: Valor financiado ajustado = (com expurgo de tarifas e/ou seguros) | AI30: =AP15 | BE30: PERCENTUAL DA TAXA COBRADADA SUPERIOR A MÉDIA | BK30: TOTAL NOMINAL DE COBRANÇAS INDEVIDAS
C31: Taxa de juros ao mês = | H31: =I18 | AD31: Taxa média de juros ao mês = | AI31: =AP16 | BE31: =H31/AI31-100% | BK31: =SUM(I9:Y13)
C32: Quantidade de parcelas = | I32: =I16 | AD32: Quantidade de parcelas = | AJ32: =I16
C34: Valor da parcela | E34: = | G34: PV | I34: x | O34: 1 | Q34: + | S34: i | U34: n | W34: x | Y34: i | AD34: Valor da parcela | AF34: = | AH34: PV | AJ34: x | AP34: 1 | AR34: + | AT34: i | AV34: n | AX34: x | AZ34: i
BE39: TAXA EFETIVAMENTE COBRADA
O42: 1 | Q42: + | S42: i | U42: n | W42: - | Y42: 1 | AP42: 1 | AR42: + | AT42: i | AV42: n | AX42: - | AZ42: 1
BE46: =RATE(I16,I17,-I15)
C50: Valor da parcela | E50: = | G50: =H30 | I50: x | O50: 1 | Q50: + | S50: =H31 | U50: =I32 | W50: x | Y50: =S50 | AD50: Valor da parcela | AF50: = | AH50: =AI30 | AJ50: x | AP50: 1 | AR50: + | AT50: =AI31 | AV50: =AJ32 | AX50: x | AZ50: =AT50
O58: 1 | Q58: + | S58: =S50 | U58: =U50 | W58: - | Y58: 1 | AP58: 1 | AR58: + | AT58: =AT50 | AV58: =AV50 | AX58: - | AZ58: 1
C66: PMT | E66: = | G66: =G50 | I66: x | O66: =O50+S50 | U66: =U50 | W66: x | Y66: =Y50 | AD66: PMT | AF66: = | AH66: =AH50 | AJ66: x | AP66: =AP50+AT50 | AV66: =AV50 | AX66: x | AZ66: =AZ50
O74: =O66 | U74: =U50 | W74: - | Y74: 1 | AP74: =AP66 | AV74: =AV50 | AX74: - | AZ74: 1
C82: PMT | E82: = | G82: =G66 | I82: x | O82: =POWER(O66,U66) | W82: x | Y82: =Y66 | AD82: PMT | AF82: = | AH82: =AH66 | AJ82: x | AP82: =POWER(AP66,AV66) | AX82: x | AZ82: =AZ66
O90: =O82 | W90: - | Y90: 1 | AP90: =AP82 | AX90: - | AZ90: 1
C98: PMT | E98: = | G98: =G82 | I98: x | O98: =O82*Y82 | AD98: PMT | AF98: = | AH98: =AH82 | AJ98: x | AP98: =AP82*AZ82
O106: =O90-Y90 | AP106: =AP90-AZ90
C114: PMT | E114: = | G114: =G98 | I114: x | K114: =O98/O106 | AD114: PMT | AF114: = | AH114: =AH98 | AJ114: x | AL114: =AP98/AP106
C122: Valor da parcela | E122: = | G122: =(G114*K114) | AD122: Valor da parcela | AF122: = | AH122: =(AH114*AL114)
C131: PARCELAS CONFORME O CONTRATO | AD131: PARCELAS RECALCULADAS | BE131: VALORES PAGOS PELO CLIENTE
C132: Parcela | D132: Vencimento | N132: Parcela cobrada | AD132: Parcela | AE132: Vencimento | AO132: Parcela recalculada | BE132: Parcela | BF132: Vencimento | BP132: Valor pago
C133: 1 | D133: =IF(C133<=$I$16, $D$6, "") | N133: =IF(C133<=$I$16, $I$17, "") | AD133: 1 | AE133: =D133 | AO133: =AH122 | BE133: 1 | BF133: =AE133 | BP133: =N133
C134: 2 | D134: =IF(C134<=$I$16, EDATE($D$6, C134-1), "") | N134: =IF(C134<=$I$16, $I$17, "") | AD134: 2 | AE134: =D134 | AO134: =AO133 | BE134: 2 | BF134: =AE134 | BP134: =BP133
C135: 3 | D135: =IF(C135<=$I$16, EDATE($D$6, C135-1), "") | N135: =IF(C135<=$I$16, $I$17, "") | AD135: 3 | AE135: =D135 | AO135: =AO134 | BE135: 3 | BF135: =AE135 | BP135: =N135
C136: 4 | D136: =IF(C136<=$I$16, EDATE($D$6, C136-1), "") | N136: =IF(C136<=$I$16, $I$17, "") | AD136: 4 | AE136: =D136 | AO136: =AO135 | BE136: 4 | BF136: =AE136 | BP136: =BP135
C137: 5 | D137: =IF(C137<=$I$16, EDATE($D$6, C137-1), "") | N137: =IF(C137<=$I$16, $I$17, "") | AD137: 5 | AE137: =D137 | AO137: =AO136 | BE137: 5 | BF137: =AE137
C138: 6 | D138: =IF(C138<=$I$16, EDATE($D$6, C138-1), "") | N138: =IF(C138<=$I$16, $I$17, "") | AD138: 6 | AE138: =D138 | AO138: =AO137 | BE138: 6 | BF138: =AE138
C139: 7 | D139: =IF(C139<=$I$16, EDATE($D$6, C139-1), "") | N139: =IF(C139<=$I$16, $I$17, "") | AD139: 7 | AE139: =D139 | AO139: =AO138 | BE139: 7 | BF139: =AE139
C140: 8 | D140: =IF(C140<=$I$16, EDATE($D$6, C140-1), "") | N140: =IF(C140<=$I$16, $I$17, "") | AD140: 8 | AE140: =D140 | AO140: =AO139 | BE140: 8 | BF140: =AE140
C141: 9 | D141: =IF(C141<=$I$16, EDATE($D$6, C141-1), "") | N141: =IF(C141<=$I$16, $I$17, "") | AD141: 9 | AE141: =D141 | AO141: =AO140 | BE141: 9 | BF141: =AE141
C142: 10 | D142: =IF(C142<=$I$16, EDATE($D$6, C142-1), "") | N142: =IF(C142<=$I$16, $I$17, "") | AD142: 10 | AE142: =D142 | AO142: =AO141 | BE142: 10 | BF142: =AE142
C143: 11 | D143: =IF(C143<=$I$16, EDATE($D$6, C143-1), "") | N143: =IF(C143<=$I$16, $I$17, "") | AD143: 11 | AE143: =D143 | AO143: =AO142 | BE143: 11 | BF143: =AE143
C144: 12 | D144: =IF(C144<=$I$16, EDATE($D$6, C144-1), "") | N144: =IF(C144<=$I$16, $I$17, "") | AD144: 12 | AE144: =D144 | AO144: =AO143 | BE144: 12 | BF144: =AE144
C145: 13 | D145: =IF(C145<=$I$16, EDATE($D$6, C145-1), "") | N145: =IF(C145<=$I$16, $I$17, "") | AD145: 13 | AE145: =D145 | AO145: =AO144 | BE145: 13 | BF145: =AE145
C146: 14 | D146: =IF(C146<=$I$16, EDATE($D$6, C146-1), "") | N146: =IF(C146<=$I$16, $I$17, "") | AD146: 14 | AE146: =D146 | AO146: =AO145 | BE146: 14 | BF146: =AE146
C147: 15 | D147: =IF(C147<=$I$16, EDATE($D$6, C147-1), "") | N147: =IF(C147<=$I$16, $I$17, "") | AD147: 15 | AE147: =D147 | AO147: =AO146 | BE147: 15 | BF147: =AE147
C148: 16 | D148: =IF(C148<=$I$16, EDATE($D$6, C148-1), "") | N148: =IF(C148<=$I$16, $I$17, "") | AD148: 16 | AE148: =D148 | AO148: =AO147 | BE148: 16 | BF148: =AE148
... C180: 48 | D180: =IF(C180<=$I$16, EDATE($D$6, C180-1), "") | N180: =IF(C180<=$I$16, $I$17, "") | AD180: 48 | AE180: =D180 | AO180: =AO179 | BE180: 48 | BF180: =AE180

Sheet PRICE 60x
C2: =DADOS!$B$2
C4: Data da pactuação: | D4: =DADOS!$B$3
C5: Data do cálculo: | D5: =TODAY()
C6: Data do 1º vencimento: | D6: =DADOS!$B$4
C7: DADOS DO CONTRATO | AD7: VALORES RECALCULADOS | BE7: SALDO RECALCULADO DESCONTANDO AS PARCELAS PAGAS
C8: Valor principal financiado = | I8: =DADOS!$B$6 | AD8: Valor principal financiado = | AP8: =I8 | BE8: Saldo devedor total do contrato = | BL8: =AP18
C9: Seguros = | I9: 0 | AD9: Seguros = | AP9: 0 | BE9: Quantidade de parcelas pagas= | BL9: =DADOS!$B$13
C10: TAC = | I10: =DADOS!$B$7 | AD10: TAC = | AP10: 0 | BE10: Valor da parcela paga = | BL10: =I17
C11: Registro = | I11: 0 | AD11: Registro = | AP11: 0 | BE11: Valor total pago pelo cliente = | BL11: =BL9*BL10
C12: Avaliação = | I12: 0 | AD12: Avaliação = | AP12: 0 | BE12: Saldo devedor atualizado = | BL12: =BL8-BL11
C13: Outros = | I13: 0 | AD13: Outros = | AP13: 0 | BE13: Quantidade de parcelas a vencer = | BL13: =I16-BL9
C14: IOF = | I14: =DADOS!$B$8 | AD14: IOF = | AP14: =I14 | BE14: Valor da parcela atual = | BL14: =BL12/BL13
C15: Valor financiado total no contrato = | I15: =SUM(I8:Y14) | AD15: Valor financiado total no contrato = | AP15: =SUM(AP8:AZ14)
C16: Quantidade de parcelas = | I16: =DADOS!$B$9 | AD16: Taxa média = | AP16: =DADOS!$B$12
C17: Valor da parcela cobrada = | I17: =DADOS!$B$10 | AD17: Valor da parcela recalculada = | AP17: =AH122 | BE17: Saldo do contrato = | BL17: =BL13*I17
C18: Taxa pactuada = | I18: =DADOS!$B$11 | AD18: Valor final recalculado do contrato = | AP18: =I16*AP17 | BE18: (-) Saldo incontroverso = | BL18: =BL13*BL14
C19: Valor final do contrato = | I19: =I16*I17 | AD19: Diferença cobrada a mais por parcela = | AP19: =I17-AP17 | BE19: Saldo controvertido total = | BL19: =BL17-BL18
AD20: Montante cobrado a mais pelo banco = | AP20: =I19-AP18 | BE20: Saldo controvertido por parcela = | BL20: =BL19/BL13
BE24: Saldo controvertido por parcela
C26: CONFORME PACTUADO | AD26: PARCELA COM TAXA MÉDIA E EXPURGO DE ABUSIVIDADES
C30: Valor financiado total = | H30: =I15 | AD30: Valor financiado ajustado = (com expurgo de tarifas e/ou seguros) | AI30: =AP15 | BE30: PERCENTUAL DA TAXA COBRADADA SUPERIOR A MÉDIA | BK30: TOTAL NOMINAL DE COBRANÇAS INDEVIDAS
C31: Taxa de juros ao mês = | H31: =I18 | AD31: Taxa média de juros ao mês = | AI31: =AP16 | BE31: =H31/AI31-100% | BK31: =SUM(I9:Y13)
C32: Quantidade de parcelas = | I32: =I16 | AD32: Quantidade de parcelas = | AJ32: =I16
C34: Valor da parcela | E34: = | G34: PV | I34: x | O34: 1 | Q34: + | S34: i | U34: n | W34: x | Y34: i | AD34: Valor da parcela | AF34: = | AH34: PV | AJ34: x | AP34: 1 | AR34: + | AT34: i | AV34: n | AX34: x | AZ34: i
BE39: TAXA EFETIVAMENTE COBRADA
O42: 1 | Q42: + | S42: i | U42: n | W42: - | Y42: 1 | AP42: 1 | AR42: + | AT42: i | AV42: n | AX42: - | AZ42: 1
BE46: =RATE(I16,I17,-I15)
C50: Valor da parcela | E50: = | G50: =H30 | I50: x | O50: 1 | Q50: + | S50: =H31 | U50: =I32 | W50: x | Y50: =S50 | AD50: Valor da parcela | AF50: = | AH50: =AI30 | AJ50: x | AP50: 1 | AR50: + | AT50: =AI31 | AV50: =AJ32 | AX50: x | AZ50: =AT50
O58: 1 | Q58: + | S58: =S50 | U58: =U50 | W58: - | Y58: 1 | AP58: 1 | AR58: + | AT58: =AT50 | AV58: =AV50 | AX58: - | AZ58: 1
C66: PMT | E66: = | G66: =G50 | I66: x | O66: =O50+S50 | U66: =U50 | W66: x | Y66: =Y50 | AD66: PMT | AF66: = | AH66: =AH50 | AJ66: x | AP66: =AP50+AT50 | AV66: =AV50 | AX66: x | AZ66: =AZ50
O74: =O66 | U74: =U50 | W74: - | Y74: 1 | AP74: =AP66 | AV74: =AV50 | AX74: - | AZ74: 1
C82: PMT | E82: = | G82: =G66 | I82: x | O82: =POWER(O66,U66) | W82: x | Y82: =Y66 | AD82: PMT | AF82: = | AH82: =AH66 | AJ82: x | AP82: =POWER(AP66,AV66) | AX82: x | AZ82: =AZ66
O90: =O82 | W90: - | Y90: 1 | AP90: =AP82 | AX90: - | AZ90: 1
C98: PMT | E98: = | G98: =G82 | I98: x | O98: =O82*Y82 | AD98: PMT | AF98: = | AH98: =AH82 | AJ98: x | AP98: =AP82*AZ82
O106: =O90-Y90 | AP106: =AP90-AZ90
C114: PMT | E114: = | G114: =G98 | I114: x | K114: =O98/O106 | AD114: PMT | AF114: = | AH114: =AH98 | AJ114: x | AL114: =AP98/AP106
C122: Valor da parcela | E122: = | G122: =(G114*K114) | AD122: Valor da parcela | AF122: = | AH122: =(AH114*AL114)
C131: PARCELAS CONFORME O CONTRATO | AD131: PARCELAS RECALCULADAS | BE131: VALORES PAGOS PELO CLIENTE
C132: Parcela | D132: Vencimento | N132: Parcela cobrada | AD132: Parcela | AE132: Vencimento | AO132: Parcela recalculada | BE132: Parcela | BF132: Vencimento | BP132: Valor pago
C133: 1 | D133: =IF(C133<=$I$16, $D$6, "") | N133: =IF(C133<=$I$16, $I$17, "") | AD133: 1 | AE133: =D133 | AO133: =AH122 | BE133: 1 | BF133: =AE133 | BP133: =N133
C134: 2 | D134: =IF(C134<=$I$16, EDATE($D$6, C134-1), "") | N134: =IF(C134<=$I$16, $I$17, "") | AD134: 2 | AE134: =D134 | AO134: =AO133 | BE134: 2 | BF134: =AE134 | BP134: =BP133
C135: 3 | D135: =IF(C135<=$I$16, EDATE($D$6, C135-1), "") | N135: =IF(C135<=$I$16, $I$17, "") | AD135: 3 | AE135: =D135 | AO135: =AO134 | BE135: 3 | BF135: =AE135
C136: 4 | D136: =IF(C136<=$I$16, EDATE($D$6, C136-1), "") | N136: =IF(C136<=$I$16, $I$17, "") | AD136: 4 | AE136: =D136 | AO136: =AO135 | BE136: 4 | BF136: =AE136
C137: 5 | D137: =IF(C137<=$I$16, EDATE($D$6, C137-1), "") | N137: =IF(C137<=$I$16, $I$17, "") | AD137: 5 | AE137: =D137 | AO137: =AO136 | BE137: 5 | BF137: =AE137
C138: 6 | D138: =IF(C138<=$I$16, EDATE($D$6, C138-1), "") | N138: =IF(C138<=$I$16, $I$17, "") | AD138: 6 | AE138: =D138 | AO138: =AO137 | BE138: 6 | BF138: =AE138
C139: 7 | D139: =IF(C139<=$I$16, EDATE($D$6, C139-1), "") | N139: =IF(C139<=$I$16, $I$17, "") | AD139: 7 | AE139: =D139 | AO139: =AO138 | BE139: 7 | BF139: =AE139
C140: 8 | D140: =IF(C140<=$I$16, EDATE($D$6, C140-1), "") | N140: =IF(C140<=$I$16, $I$17, "") | AD140: 8 | AE140: =D140 | AO140: =AO139 | BE140: 8 | BF140: =AE140
C141: 9 | D141: =IF(C141<=$I$16, EDATE($D$6, C141-1), "") | N141: =IF(C141<=$I$16, $I$17, "") | AD141: 9 | AE141: =D141 | AO141: =AO140 | BE141: 9 | BF141: =AE141
C142: 10 | D142: =IF(C142<=$I$16, EDATE($D$6, C142-1), "") | N142: =IF(C142<=$I$16, $I$17, "") | AD142: 10 | AE142: =D142 | AO142: =AO141 | BE142: 10 | BF142: =AE142
C143: 11 | D143: =IF(C143<=$I$16, EDATE($D$6, C143-1), "") | N143: =IF(C143<=$I$16, $I$17, "") | AD143: 11 | AE143: =D143 | AO143: =AO142 | BE143: 11 | BF143: =AE143
C144: 12 | D144: =IF(C144<=$I$16, EDATE($D$6, C144-1), "") | N144: =IF(C144<=$I$16, $I$17, "") | AD144: 12 | AE144: =D144 | AO144: =AO143 | BE144: 12 | BF144: =AE144
C145: 13 | D145: =IF(C145<=$I$16, EDATE($D$6, C145-1), "") | N145: =IF(C145<=$I$16, $I$17, "") | AD145: 13 | AE145: =D145 | AO145: =AO144 | BE145: 13 | BF145: =AE145
C146: 14 | D146: =IF(C146<=$I$16, EDATE($D$6, C146-1), "") | N146: =IF(C146<=$I$16, $I$17, "") | AD146: 14 | AE146: =D146 | AO146: =AO145 | BE146: 14 | BF146: =AE146
... C191: 59 | D191: =IF(C191<=$I$16, EDATE($D$6, C191-1), "") | N191: =IF(C191<=$I$16, $I$17, "") | AD191: 59 | AE191: =D191 | AO191: =AO190 | BE191: 59 | BF191: =AE191
C192: 60 | D192: =IF(C192<=$I$16, EDATE($D$6, C192-1), "") | N192: =IF(C192<=$I$16, $I$17, "") | AD192: 60 | AE192: =D192 | AO192: =AO191 | BE192: 60 | BG192: =AE192
